kitanaqa/__init__.py
kitanaqa/augment/__init__.py
kitanaqa/augment/augment_squad.py
kitanaqa/augment/generators.py
kitanaqa/augment/term_replacement.py
kitanaqa/support/__init__.py
kitanaqa/support/counter-fitted-vectors.txt.zip
kitanaqa/support/dev-v1.1.json
kitanaqa/support/missp.json
kitanaqa/support/train-v1.1.json
kitanaqa/support/unittest-squad.json
kitanaqa/trainer/__init__.py
kitanaqa/trainer/alum_squad_processor.py
kitanaqa/trainer/arguments.py
kitanaqa/trainer/custom_schedulers.py
kitanaqa/trainer/run_pipeline.py
kitanaqa/trainer/train.py
kitanaqa/trainer/utils.py
kitanaqa-0.1.0.dist-info/LICENSE
kitanaqa-0.1.0.dist-info/METADATA
kitanaqa-0.1.0.dist-info/WHEEL
kitanaqa-0.1.0.dist-info/top_level.txt
kitanaqa-0.1.0.dist-info/RECORD
