Metadata-Version: 2.1
Name: kitanaqa
Version: 0.1.0
Summary: Adversarial Training and Data Augmentation for Neural Question-Answering Models
Home-page: https://github.com/searchableai/KitanaQA
Author: Senzeyu Zhang, Mostafa Mirshekari, Aaron Sisto
Author-email: aaron@searchable.ai
License: Apache
Keywords: NLP BERT adversarial training data augmentation deep learning pytorch google
Platform: UNKNOWN
Requires-Python: >=3.7.0
Requires-Dist: config
Requires-Dist: nltk
Requires-Dist: numpy (<1.18.0,>=1.14.0)
Requires-Dist: stop-words
Requires-Dist: torch (>=1.5.1)
Requires-Dist: transformers (==3.1.0)
Requires-Dist: prefect (==0.13.4)
Requires-Dist: pendulum (==2.0.5)
Requires-Dist: dataclasses (==0.6)
Provides-Extra: dev
Requires-Dist: pytest ; extra == 'dev'
Requires-Dist: pytest-pep8 ; extra == 'dev'
Requires-Dist: pytest-cov ; extra == 'dev'
